ixc_whitenoise/__init__.py
ixc_whitenoise/middleware.py
ixc_whitenoise/monkeypatch_django16.py
ixc_whitenoise/pipeline.py
ixc_whitenoise/storage.py
ixc_whitenoise-0.6.1.dist-info/DESCRIPTION.rst
ixc_whitenoise-0.6.1.dist-info/METADATA
ixc_whitenoise-0.6.1.dist-info/RECORD
ixc_whitenoise-0.6.1.dist-info/WHEEL
ixc_whitenoise-0.6.1.dist-info/metadata.json
ixc_whitenoise-0.6.1.dist-info/top_level.txt
