Metadata-Version: 2.0
Name: ixc-whitenoise
Version: 0.6.1
Summary: Improvements to WhiteNoise.
Home-page: https://github.com/ixc/ixc-whitenoise
Author: Interaction Consortium
Author-email: studio@interaction.net.au
License: MIT
Platform: UNKNOWN
Requires-Dist: whitenoise (>=3.1)
Provides-Extra: pipeline
Requires-Dist: django-pipeline; extra == 'pipeline'
